bcn_rainfall_core/__init__.py
bcn_rainfall_core/config.py
bcn_rainfall_core/rainfall.py
bcn_rainfall_core/models/__init__.py
bcn_rainfall_core/models/monthly_rainfall.py
bcn_rainfall_core/models/seasonal_rainfall.py
bcn_rainfall_core/models/yearly_rainfall.py
bcn_rainfall_core/utils/__init__.py
bcn_rainfall_core/utils/base_config.py
bcn_rainfall_core/utils/custom_exceptions.py
bcn_rainfall_core/utils/dataframe_operations.py
bcn_rainfall_core/utils/enums.py
bcn_rainfall_core/utils/plotly_figures.py
bcn_rainfall_core/utils/rainfall_metrics.py
bcn_rainfall_core/utils/schemas.py
bcn_rainfall_core-1.0.7.dist-info/METADATA
bcn_rainfall_core-1.0.7.dist-info/WHEEL
bcn_rainfall_core-1.0.7.dist-info/top_level.txt
bcn_rainfall_core-1.0.7.dist-info/RECORD
