Metadata-Version: 2.4
Name: bcn-rainfall-core
Version: 1.0.7
Summary: Tools to load and manipulate rainfall data from the city of Barcelona, Catalunya.
Author-email: Paul Charles <paul.charles@tutanota.com>
Requires-Python: >=3.12
Requires-Dist: coverage~=7.6.9
Requires-Dist: numpy~=2.1.3
Requires-Dist: pandas~=2.2.2
Requires-Dist: plotly~=5.24.1
Requires-Dist: pre-commit~=4.0.1
Requires-Dist: pydantic~=2.8.2
Requires-Dist: pytest~=8.3.4
Requires-Dist: pyyaml~=6.0.2
Requires-Dist: scikit-learn~=1.5.1
Requires-Dist: scipy~=1.14.1
